mkTranslation/__init__.py
mkTranslation/adapters.py
mkTranslation/client.py
mkTranslation/compat.py
mkTranslation/constants.py
mkTranslation/gtoken.py
mkTranslation/model.py
mkTranslation/models.py
mkTranslation/network.py
mkTranslation/translateDoc.py
mkTranslation/translate_chinese.py
mkTranslation/translate_google.py
mkTranslation/translate_youdao.py
mkTranslation/translator.py
mkTranslation/urls.py
mkTranslation/utils.py
mkTranslation/zh_data.py
mkTranslation-1.6.1.data/scripts/trans
mkTranslation-1.6.1.data/scripts/translate
mkTranslation-1.6.1.dist-info/LICENSE
mkTranslation-1.6.1.dist-info/METADATA
mkTranslation-1.6.1.dist-info/WHEEL
mkTranslation-1.6.1.dist-info/top_level.txt
mkTranslation-1.6.1.dist-info/RECORD
