Metadata-Version: 2.1
Name: mkTranslation
Version: 1.6.1
Summary: Command line tools translated using Google、Youdao and i18ns.com
Home-page: https://github.com/mythkiven/mkTranslate
Author: MythKiven
Author-email: mythkiven@qq.com
License: MIT
Keywords: google translate translator
Platform: UNKNOWN
Requires-Dist: requests
Provides-Extra: h2
Requires-Dist: hyper ; extra == 'h2'
